[1,["ecpdLyjvZBwrvm+cedCcQy","c8MneFfdlHAJcMAUcotOWE","ceXrxOzixMO5sgROpaG9se","bbG2yPoW9Oha4mITOq7R6R","d2XuKZl4tD46eER5v9otKm","e2luu/KvVKlYdD2BpQXV1D","02delMVqdBD70a/HSD99FK","a2MjXRFdtLlYQ5ouAFv/+R","bf8OYC7g5CrZ3PIqArButo","beYieAu3lKgZBi2SoFsS8g","74gMrp+0ZJPYZnc8PDgNoj","3eEtFniPRAJ7b6ClSO0D93","bbqBfKXARISLupDcyeenXd","fe5xp6DnlJa7HP82gCjshl","ecbwcwa5JGxZ7nMwn+/30o","3cARmtUxdNn7NkbCSx2ik/","b4xlyE4e5BYoRBI0xvk285","38G5jWISNA46t2u2afq8u7","68EM7vaP5MHKeTUujGTkmA","efItt5+b1EXqafFA1k/VRC","bfdAaGdphGtYbVOYxwf1yY","76buYoI0RKOa0znM1zFlNB","d4H86PzCFE/bmSFJvcfbAU"],["node","_spriteFrame","_textureSetter","root","showTextLabel","data","_normalMaterial"],["cc.SpriteFrame",["cc.Node",["_name","_active","_opacity","_prefab","_components","_contentSize","_parent","_trs","_children","_color"],0,4,9,5,1,7,2,5],["cc.PrefabInfo",["fileId","root"],2,1],["cc.Button",["_N$transition","node","clickEvents","_normalMaterial"],2,1,9,6],["cc.Sprite",["_sizeMode","node","_materials","_spriteFrame"],2,1,3,6],["cc.Prefab",["_name"],2],["cc.Node",["_name","_parent","_components","_prefab","_contentSize","_trs"],2,1,2,4,5,7],["b7e7dJr58xMyb5svqccSpa2",["node","showTextLabel","spriteList"],3,1,1,3],["cc.ClickEvent",["_componentId","handler","target"],1,1],["cc.BlockInputEvents",["node"],3,1],["cc.Label",["_string","_styleFlags","_N$horizontalAlign","_N$verticalAlign","_N$overflow","node","_materials"],-2,1,3]],[[2,0,1,2],[4,0,1,2,3,2],[4,1,2,3,1],[1,0,1,6,4,3,5,7,3],[1,0,6,8,4,3,5,7,2],[1,0,1,6,4,3,5,3],[1,0,6,8,3,7,2],[1,0,6,4,3,5,7,2],[1,0,6,4,3,5,2],[8,0,1,2,3],[5,0,2],[1,0,8,4,3,5,2],[1,0,2,6,4,3,9,5,3],[6,0,1,2,3,4,5,2],[7,0,1,2,1],[2,1,1],[3,0,1,2,2],[3,0,1,2,3,2],[9,0,1],[10,0,1,2,3,4,5,6,6]],[[[{"name":"an","rect":[1,1,226,65],"offset":[0,0],"originalSize":[228,67],"capInsets":[0,0,0,0]}],[0],0,[0],[2],[3]],[[{"name":"label2","rect":[0,0,429,32],"offset":[0,0.5],"originalSize":[429,33],"capInsets":[0,0,0,0]}],[0],0,[0],[2],[4]],[[{"name":"close","rect":[0,0,60,60],"offset":[0,0],"originalSize":[60,60],"capInsets":[0,0,0,0]}],[0],0,[0],[2],[5]],[[{"name":"default_sprite_splash","rect":[0,0,2,2],"offset":[0,0],"originalSize":[2,2],"capInsets":[0,0,0,0]}],[0],0,[0],[2],[6]],[[[10,"hongBaoCunQianGuan"],[11,"hongBaoCunQianGuan",[-4,-5,-6,-7,-8,-9,-10],[[14,-3,-2,[34,35]]],[15,-1],[5,750,1600]],[6,"hongbaoAni",1,[-11,-12,-13,-14,-15,-16,-17],[0,"22FPHXWJZG7oWOlr8Bl9GE",1],[0,-342.044,0,0,0,0,1,1,1,1]],[4,"clickBtn",1,[-19,-20],[[16,3,-18,[[9,"b7e7dJr58xMyb5svqccSpa2","clickLingQu",1]]]],[0,"7d1uxX1fdIK5Z4gVeShzwS",1],[5,301,105],[0,-350,0,0,0,0,1,1,1,0]],[12,"bg",87,1,[[1,0,-21,[0],1],[18,-22]],[0,"26IisqI2xAApGgbtVnuYEd",1],[4,4278190080],[5,750,1800]],[4,"pigCunQianGuan",1,[-24],[[2,-23,[4],5]],[0,"3bB/Yhg+hP7Zxi3yhYzGa0",1],[5,457,431],[0,136.798,0,0,0,0,1,1,1,1]],[4,"showYesterday",1,[-26],[[2,-25,[7],8]],[0,"b5EpmFCoNHy6ksYJL9Oi+c",1],[5,226,66],[0,-130,0,0,0,0,1,1,1,1]],[7,"closeBtn",1,[[2,-27,[9],10],[17,3,-28,[[9,"b7e7dJr58xMyb5svqccSpa2","clickClose",1]],11]],[0,"bfbKL4V8tLXoK7KALh18LU",1],[5,60,60],[260,500,0,0,0,0,1,1,1,0]],[6,"label",1,[-29,-30],[0,"11Da1VtNhFUoqeBb6PR8oR",1],[0,-250,0,0,0,0,1,1,1,1]],[7,"titleLable",5,[[2,-31,[2],3]],[0,"39QlKRwpVCi6bepNKmUrGq",1],[5,429,145],[0,280,0,0,0,0,1,1,1,1]],[13,"label",6,[-32],[0,"76shVbunNI/5I1lrnIZAXq",1],[5,120,40],[30,0,0,0,0,0,1,1,1,1]],[19,"0",1,1,1,1,10,[6]],[8,"nowLabel",8,[[2,-33,[12],13]],[0,"b4FcMzalBMJrehCZUrktKf",1],[5,429,32]],[5,"lastLabel",false,8,[[2,-34,[14],15]],[0,"97MOUVpUBDgZFazRDQCNVz",1],[5,615,67]],[8,"last",3,[[2,-35,[16],17]],[0,"99AUSwrm1DA4eqyatynvJ/",1],[5,301,105]],[5,"now",false,3,[[2,-36,[18],19]],[0,"5ddm9t34dL1rlexp8PVfrd",1],[5,301,105]],[5,"hongbao",false,2,[[1,0,-37,[20],21]],[0,"2bojQ0pmFBqZ2J7fa1ec/e",1],[5,50,50]],[3,"hongbao",false,2,[[1,0,-38,[22],23]],[0,"b1pbxJ6oxGuLIw2IwcK2Lx",1],[5,50,50],[59.437,0,0,0,0,0,1,1,1,1]],[3,"hongbao",false,2,[[1,0,-39,[24],25]],[0,"903V8jvDFC07HwFCgoDiXC",1],[5,50,50],[-10.872,-74.845,0,0,0,0,1,1,1,1]],[3,"hongbao",false,2,[[1,0,-40,[26],27]],[0,"dafDrUGFhOAb7ytqUu/VWg",1],[5,50,50],[-69.109,-48.359,0,0,0,0,1,1,1,1]],[3,"hongbao",false,2,[[1,0,-41,[28],29]],[0,"305bzSQURCMadWs7vsU52R",1],[5,50,50],[23.919,61.199,0,0,0,0,1,1,1,1]],[3,"hongbao",false,2,[[1,0,-42,[30],31]],[0,"ac1BbK49NDKbIioZNwkzzg",1],[5,50,50],[-50.74,24.686,0,0,0,0,1,1,1,1]],[3,"hongbao",false,2,[[1,0,-43,[32],33]],[0,"b6YwHQHidGRa9l4shZ4BiF",1],[5,50,50],[53.12,-66.492,0,0,0,0,1,1,1,1]]],0,[0,3,1,0,4,11,0,0,1,0,-1,4,0,-2,5,0,-3,6,0,-4,7,0,-5,8,0,-6,3,0,-7,2,0,-1,16,0,-2,17,0,-3,18,0,-4,19,0,-5,20,0,-6,21,0,-7,22,0,0,3,0,-1,14,0,-2,15,0,0,4,0,0,4,0,0,5,0,-1,9,0,0,6,0,-1,10,0,0,7,0,0,7,0,-1,12,0,-2,13,0,0,9,0,-1,11,0,0,12,0,0,13,0,0,14,0,0,15,0,0,16,0,0,17,0,0,18,0,0,19,0,0,20,0,0,21,0,0,22,0,5,1,43],[0,0,0,0,0,0,0,0,0,0,0,0,0,0,0,0,0,0,0,0,0,0,0,0,0,0,0,0,0,0,0,0,0,0,0,0],[-1,1,-1,1,-1,1,-1,-1,1,-1,1,6,-1,1,-1,1,-1,1,-1,1,-1,1,-1,1,-1,1,-1,1,-1,1,-1,1,-1,1,-1,-2],[0,7,0,8,0,9,0,0,2,0,10,0,0,11,0,12,0,13,0,14,0,1,0,1,0,1,0,1,0,1,0,1,0,1,15,2]],[[{"name":"label","rect":[0,0,615,67],"offset":[0,0],"originalSize":[615,67],"capInsets":[0,0,0,0]}],[0],0,[0],[2],[16]],[[{"name":"hongbaopig","rect":[0,0,457,431],"offset":[0,0],"originalSize":[457,431],"capInsets":[0,0,0,0]}],[0],0,[0],[2],[17]],[[{"name":"titleLable","rect":[0,0,429,145],"offset":[0,0],"originalSize":[429,145],"capInsets":[0,0,0,0]}],[0],0,[0],[2],[18]],[[{"name":"hongbao","rect":[24,16,79,90],"offset":[1.5,0.5],"originalSize":[124,123],"capInsets":[0,0,0,0]}],[0],0,[0],[2],[19]],[[{"name":"ming","rect":[0,0,226,66],"offset":[0,0],"originalSize":[226,66],"capInsets":[0,0,0,0]}],[0],0,[0],[2],[20]],[[{"name":"lingqu","rect":[0,0,301,105],"offset":[0,0],"originalSize":[301,105],"capInsets":[0,0,0,0]}],[0],0,[0],[2],[21]],[[{"name":"mingrikeling","rect":[0,0,301,105],"offset":[0,0],"originalSize":[301,105],"capInsets":[0,0,0,0]}],[0],0,[0],[2],[22]]]]